[{"id":"ygo-482378","name":"Spright Blue (UTR)","set":"OTS Tournament Pack 21","setId":"OP21","number":"OP21-EN001","setTotal":27,"setReleaseDate":"2023-02-08","rarity":"Ultimate Rare","artist":"","language":"en","image":"https://tcgplayer-cdn.tcgplayer.com/product/482378_in_1000x1000.jpg","variants":["Unlimited"],"cardType":"Effect Monster","attribute":"DARK","monsterType":"Thunder","atk":"1100","def":"1000","setLogo":"https://tcgplayer-cdn.tcgplayer.com/product/482378_in_1000x1000.jpg"},{"id":"ygo-482379","name":"Tearlaments Reinoheart (UTR)","set":"OTS Tournament Pack 21","setId":"OP21","number":"OP21-EN002","setTotal":27,"setReleaseDate":"2023-02-08","rarity":"Ultimate Rare","artist":"","language":"en","image":"https://tcgplayer-cdn.tcgplayer.com/product/482379_in_1000x1000.jpg","variants":["Unlimited"],"cardType":"Effect Monster","attribute":"WATER","monsterType":"Warrior","atk":"1500","def":"2100","setLogo":"https://tcgplayer-cdn.tcgplayer.com/product/482378_in_1000x1000.jpg"},{"id":"ygo-482380","name":"Kashtira Fenrir (UTR)","set":"OTS Tournament Pack 21","setId":"OP21","number":"OP21-EN003","setTotal":27,"setReleaseDate":"2023-02-08","rarity":"Ultimate Rare","artist":"","language":"en","image":"https://tcgplayer-cdn.tcgplayer.com/product/482380_in_1000x1000.jpg","variants":["Unlimited"],"cardType":"Effect Monster","attribute":"EARTH","monsterType":"Psychic","atk":"2400","def":"2400","setLogo":"https://tcgplayer-cdn.tcgplayer.com/product/482378_in_1000x1000.jpg"},{"id":"ygo-482431","name":"Spright Red","set":"OTS Tournament Pack 21","setId":"OP21","number":"OP21-EN004","setTotal":27,"setReleaseDate":"2023-02-08","rarity":"Super Rare","artist":"","language":"en","image":"https://tcgplayer-cdn.tcgplayer.com/product/482431_in_1000x1000.jpg","variants":["Unlimited"],"cardType":"Effect Monster","attribute":"FIRE","monsterType":"Thunder","atk":"1200","def":"1800","setLogo":"https://tcgplayer-cdn.tcgplayer.com/product/482378_in_1000x1000.jpg"},{"id":"ygo-482432","name":"Tearlaments Merrli","set":"OTS Tournament Pack 21","setId":"OP21","number":"OP21-EN005","setTotal":27,"setReleaseDate":"2023-02-08","rarity":"Super Rare","artist":"","language":"en","image":"https://tcgplayer-cdn.tcgplayer.com/product/482432_in_1000x1000.jpg","variants":["Unlimited"],"cardType":"Effect Monster","attribute":"DARK","monsterType":"Aqua","atk":"800","def":"2000","setLogo":"https://tcgplayer-cdn.tcgplayer.com/product/482378_in_1000x1000.jpg"},{"id":"ygo-482433","name":"Tearlaments Havnis","set":"OTS Tournament Pack 21","setId":"OP21","number":"OP21-EN006","setTotal":27,"setReleaseDate":"2023-02-08","rarity":"Super Rare","artist":"","language":"en","image":"https://tcgplayer-cdn.tcgplayer.com/product/482433_in_1000x1000.jpg","variants":["Unlimited"],"cardType":"Effect Monster","attribute":"DARK","monsterType":"Aqua","atk":"1600","def":"1000","setLogo":"https://tcgplayer-cdn.tcgplayer.com/product/482378_in_1000x1000.jpg"},{"id":"ygo-482434","name":"Tobari the Sky Ninja","set":"OTS Tournament Pack 21","setId":"OP21","number":"OP21-EN007","setTotal":27,"setReleaseDate":"2023-02-08","rarity":"Super Rare","artist":"","language":"en","image":"https://tcgplayer-cdn.tcgplayer.com/product/482434_in_1000x1000.jpg","variants":["Unlimited"],"cardType":"Effect Monster","attribute":"EARTH","monsterType":"Winged Beast","atk":"0","def":"0","setLogo":"https://tcgplayer-cdn.tcgplayer.com/product/482378_in_1000x1000.jpg"},{"id":"ygo-482435","name":"Scareclaw Kashtira","set":"OTS Tournament Pack 21","setId":"OP21","number":"OP21-EN008","setTotal":27,"setReleaseDate":"2023-02-08","rarity":"Super Rare","artist":"","language":"en","image":"https://tcgplayer-cdn.tcgplayer.com/product/482435_in_1000x1000.jpg","variants":["Unlimited"],"cardType":"Effect Monster","attribute":"EARTH","monsterType":"Psychic","atk":"0","def":"2600","setLogo":"https://tcgplayer-cdn.tcgplayer.com/product/482378_in_1000x1000.jpg"},{"id":"ygo-482436","name":"Number 29: Mannequin Cat","set":"OTS Tournament Pack 21","setId":"OP21","number":"OP21-EN009","setTotal":27,"setReleaseDate":"2023-02-08","rarity":"Super Rare","artist":"","language":"en","image":"https://tcgplayer-cdn.tcgplayer.com/product/482436_in_1000x1000.jpg","variants":["Unlimited"],"cardType":"Effect Xyz Monster","attribute":"LIGHT","monsterType":"Beast","atk":"2000","def":"900","setLogo":"https://tcgplayer-cdn.tcgplayer.com/product/482378_in_1000x1000.jpg"},{"id":"ygo-482437","name":"Epurrely Happiness","set":"OTS Tournament Pack 21","setId":"OP21","number":"OP21-EN010","setTotal":27,"setReleaseDate":"2023-02-08","rarity":"Super Rare","artist":"","language":"en","image":"https://tcgplayer-cdn.tcgplayer.com/product/482437_in_1000x1000.jpg","variants":["Unlimited"],"cardType":"Effect Xyz Monster","attribute":"LIGHT","monsterType":"Fairy","atk":"2000","def":"100","setLogo":"https://tcgplayer-cdn.tcgplayer.com/product/482378_in_1000x1000.jpg"},{"id":"ygo-482438","name":"Rescue-ACE HQ","set":"OTS Tournament Pack 21","setId":"OP21","number":"OP21-EN011","setTotal":27,"setReleaseDate":"2023-02-08","rarity":"Super Rare","artist":"","language":"en","image":"https://tcgplayer-cdn.tcgplayer.com/product/482438_in_1000x1000.jpg","variants":["Unlimited"],"cardType":"Field Spell","attribute":"SPELL","monsterType":null,"atk":null,"def":null,"setLogo":"https://tcgplayer-cdn.tcgplayer.com/product/482378_in_1000x1000.jpg"},{"id":"ygo-482439","name":"Light of the Branded","set":"OTS Tournament Pack 21","setId":"OP21","number":"OP21-EN012","setTotal":27,"setReleaseDate":"2023-02-08","rarity":"Super Rare","artist":"","language":"en","image":"https://tcgplayer-cdn.tcgplayer.com/product/482439_in_1000x1000.jpg","variants":["Unlimited"],"cardType":"Quick-Play Spell","attribute":"SPELL","monsterType":null,"atk":null,"def":null,"setLogo":"https://tcgplayer-cdn.tcgplayer.com/product/482378_in_1000x1000.jpg"},{"id":"ygo-482440","name":"Mysterious Puppeteer","set":"OTS Tournament Pack 21","setId":"OP21","number":"OP21-EN013","setTotal":27,"setReleaseDate":"2023-02-08","rarity":"Common","artist":"","language":"en","image":"https://tcgplayer-cdn.tcgplayer.com/product/482440_in_1000x1000.jpg","variants":["Unlimited"],"cardType":"Effect Monster","attribute":"EARTH","monsterType":"Warrior","atk":"1000","def":"1500","setLogo":"https://tcgplayer-cdn.tcgplayer.com/product/482378_in_1000x1000.jpg"},{"id":"ygo-482445","name":"Testudo erat Numen","set":"OTS Tournament Pack 21","setId":"OP21","number":"OP21-EN014","setTotal":27,"setReleaseDate":"2023-02-08","rarity":"Common","artist":"","language":"en","image":"https://tcgplayer-cdn.tcgplayer.com/product/482445_in_1000x1000.jpg","variants":["Unlimited"],"cardType":"Effect Monster","attribute":"WATER","monsterType":"Aqua","atk":"0","def":"1800","setLogo":"https://tcgplayer-cdn.tcgplayer.com/product/482378_in_1000x1000.jpg"},{"id":"ygo-482448","name":"Abyss Actor - Curtain Raiser","set":"OTS Tournament Pack 21","setId":"OP21","number":"OP21-EN015","setTotal":27,"setReleaseDate":"2023-02-08","rarity":"Common","artist":"","language":"en","image":"https://tcgplayer-cdn.tcgplayer.com/product/482448_in_1000x1000.jpg","variants":["Unlimited"],"cardType":"Effect Pendulum Monster","attribute":"DARK","monsterType":"Fiend","atk":"1100","def":"1000","setLogo":"https://tcgplayer-cdn.tcgplayer.com/product/482378_in_1000x1000.jpg"},{"id":"ygo-482449","name":"Mudragon of the Swamp","set":"OTS Tournament Pack 21","setId":"OP21","number":"OP21-EN016","setTotal":27,"setReleaseDate":"2023-02-08","rarity":"Common","artist":"","language":"en","image":"https://tcgplayer-cdn.tcgplayer.com/product/482449_in_1000x1000.jpg","variants":["Unlimited"],"cardType":"Effect Fusion Monster","attribute":"WATER","monsterType":"Wyrm","atk":"1900","def":"1600","setLogo":"https://tcgplayer-cdn.tcgplayer.com/product/482378_in_1000x1000.jpg"},{"id":"ygo-482451","name":"Gishki Aquamirror","set":"OTS Tournament Pack 21","setId":"OP21","number":"OP21-EN017","setTotal":27,"setReleaseDate":"2023-02-08","rarity":"Common","artist":"","language":"en","image":"https://tcgplayer-cdn.tcgplayer.com/product/482451_in_1000x1000.jpg","variants":["Unlimited"],"cardType":"Ritual Spell","attribute":"SPELL","monsterType":null,"atk":null,"def":null,"setLogo":"https://tcgplayer-cdn.tcgplayer.com/product/482378_in_1000x1000.jpg"},{"id":"ygo-482455","name":"Contact with the Aquamirror","set":"OTS Tournament Pack 21","setId":"OP21","number":"OP21-EN018","setTotal":27,"setReleaseDate":"2023-02-08","rarity":"Common","artist":"","language":"en","image":"https://tcgplayer-cdn.tcgplayer.com/product/482455_in_1000x1000.jpg","variants":["Unlimited"],"cardType":"Normal Spell","attribute":"SPELL","monsterType":null,"atk":null,"def":null,"setLogo":"https://tcgplayer-cdn.tcgplayer.com/product/482378_in_1000x1000.jpg"},{"id":"ygo-482457","name":"Photon Sanctuary","set":"OTS Tournament Pack 21","setId":"OP21","number":"OP21-EN019","setTotal":27,"setReleaseDate":"2023-02-08","rarity":"Common","artist":"","language":"en","image":"https://tcgplayer-cdn.tcgplayer.com/product/482457_in_1000x1000.jpg","variants":["Unlimited"],"cardType":"Normal Spell","attribute":"SPELL","monsterType":null,"atk":null,"def":null,"setLogo":"https://tcgplayer-cdn.tcgplayer.com/product/482378_in_1000x1000.jpg"},{"id":"ygo-482460","name":"Galaxy Expedition","set":"OTS Tournament Pack 21","setId":"OP21","number":"OP21-EN020","setTotal":27,"setReleaseDate":"2023-02-08","rarity":"Common","artist":"","language":"en","image":"https://tcgplayer-cdn.tcgplayer.com/product/482460_in_1000x1000.jpg","variants":["Unlimited"],"cardType":"Normal Spell","attribute":"SPELL","monsterType":null,"atk":null,"def":null,"setLogo":"https://tcgplayer-cdn.tcgplayer.com/product/482378_in_1000x1000.jpg"},{"id":"ygo-482463","name":"Sacred Sword of Seven Stars","set":"OTS Tournament Pack 21","setId":"OP21","number":"OP21-EN021","setTotal":27,"setReleaseDate":"2023-02-08","rarity":"Common","artist":"","language":"en","image":"https://tcgplayer-cdn.tcgplayer.com/product/482463_in_1000x1000.jpg","variants":["Unlimited"],"cardType":"Normal Spell","attribute":"SPELL","monsterType":null,"atk":null,"def":null,"setLogo":"https://tcgplayer-cdn.tcgplayer.com/product/482378_in_1000x1000.jpg"},{"id":"ygo-482465","name":"Time-Space Trap Hole","set":"OTS Tournament Pack 21","setId":"OP21","number":"OP21-EN022","setTotal":27,"setReleaseDate":"2023-02-08","rarity":"Common","artist":"","language":"en","image":"https://tcgplayer-cdn.tcgplayer.com/product/482465_in_1000x1000.jpg","variants":["Unlimited"],"cardType":"Normal Trap","attribute":"TRAP","monsterType":null,"atk":null,"def":null,"setLogo":"https://tcgplayer-cdn.tcgplayer.com/product/482378_in_1000x1000.jpg"},{"id":"ygo-482466","name":"Mischief of the Gnomes","set":"OTS Tournament Pack 21","setId":"OP21","number":"OP21-EN023","setTotal":27,"setReleaseDate":"2023-02-08","rarity":"Common","artist":"","language":"en","image":"https://tcgplayer-cdn.tcgplayer.com/product/482466_in_1000x1000.jpg","variants":["Unlimited"],"cardType":"Normal Trap","attribute":"TRAP","monsterType":null,"atk":null,"def":null,"setLogo":"https://tcgplayer-cdn.tcgplayer.com/product/482378_in_1000x1000.jpg"},{"id":"ygo-482467","name":"Trap Hole of Spikes","set":"OTS Tournament Pack 21","setId":"OP21","number":"OP21-EN024","setTotal":27,"setReleaseDate":"2023-02-08","rarity":"Common","artist":"","language":"en","image":"https://tcgplayer-cdn.tcgplayer.com/product/482467_in_1000x1000.jpg","variants":["Unlimited"],"cardType":"Normal Trap","attribute":"TRAP","monsterType":null,"atk":null,"def":null,"setLogo":"https://tcgplayer-cdn.tcgplayer.com/product/482378_in_1000x1000.jpg"},{"id":"ygo-482469","name":"Network Trap Hole","set":"OTS Tournament Pack 21","setId":"OP21","number":"OP21-EN025","setTotal":27,"setReleaseDate":"2023-02-08","rarity":"Common","artist":"","language":"en","image":"https://tcgplayer-cdn.tcgplayer.com/product/482469_in_1000x1000.jpg","variants":["Unlimited"],"cardType":"Normal Trap","attribute":"TRAP","monsterType":null,"atk":null,"def":null,"setLogo":"https://tcgplayer-cdn.tcgplayer.com/product/482378_in_1000x1000.jpg"},{"id":"ygo-482474","name":"Amaze Attraction Majestic Merry-Go-Round","set":"OTS Tournament Pack 21","setId":"OP21","number":"OP21-EN026","setTotal":27,"setReleaseDate":"2023-02-08","rarity":"Common","artist":"","language":"en","image":"https://tcgplayer-cdn.tcgplayer.com/product/482474_in_1000x1000.jpg","variants":["Unlimited"],"cardType":"Normal Trap","attribute":"TRAP","monsterType":null,"atk":null,"def":null,"setLogo":"https://tcgplayer-cdn.tcgplayer.com/product/482378_in_1000x1000.jpg"},{"id":"ygo-482475","name":"Black Feather Counter","set":"OTS Tournament Pack 21","setId":"OP21","number":"OP21-EN027","setTotal":27,"setReleaseDate":"2023-02-08","rarity":"Super Rare","artist":"","language":"en","image":"https://tcgplayer-cdn.tcgplayer.com/product/482475_in_1000x1000.jpg","variants":["Unlimited"],"cardType":"Counter","attribute":null,"monsterType":null,"atk":null,"def":null,"setLogo":"https://tcgplayer-cdn.tcgplayer.com/product/482378_in_1000x1000.jpg"}]